marzeqdiscord/__init__.py
marzeqdiscord/commandparser.py
marzeqdiscord/events.py
marzeqdiscord-0.1.1.dist-info/LICENSE
marzeqdiscord-0.1.1.dist-info/METADATA
marzeqdiscord-0.1.1.dist-info/WHEEL
marzeqdiscord-0.1.1.dist-info/top_level.txt
marzeqdiscord-0.1.1.dist-info/RECORD
