Metadata-Version: 2.1
Name: marzeqdiscord
Version: 0.1.1
Summary: Custom extensions for discord.py
Home-page: https://github.com/marzeq/marzeqdiscord
Author: marzeq
Author-email: marzeqmarzeq@gmail.com
License: Creative Commons Attribution NonCommercial (CC-BY-NC)
Platform: UNKNOWN
Requires-Dist: discord.py (>=1.5.1)
